stream_translator_gpt/__init__.py
stream_translator_gpt/__main__.py
stream_translator_gpt/audio_getter.py
stream_translator_gpt/audio_slicer.py
stream_translator_gpt/audio_transcriber.py
stream_translator_gpt/common.py
stream_translator_gpt/filters.py
stream_translator_gpt/llm_translator.py
stream_translator_gpt/main.py
stream_translator_gpt/result_exporter.py
stream_translator_gpt/silero_vad.jit
stream_translator_gpt/simul_streaming/simulstreaming_whisper.py
stream_translator_gpt/simul_streaming/token_buffer.py
stream_translator_gpt/simul_streaming/simul_whisper/__init__.py
stream_translator_gpt/simul_streaming/simul_whisper/beam.py
stream_translator_gpt/simul_streaming/simul_whisper/config.py
stream_translator_gpt/simul_streaming/simul_whisper/eow_detection.py
stream_translator_gpt/simul_streaming/simul_whisper/generation_progress.py
stream_translator_gpt/simul_streaming/simul_whisper/simul_whisper.py
stream_translator_gpt/simul_streaming/simul_whisper/whisper/__init__.py
stream_translator_gpt/simul_streaming/simul_whisper/whisper/audio.py
stream_translator_gpt/simul_streaming/simul_whisper/whisper/decoding.py
stream_translator_gpt/simul_streaming/simul_whisper/whisper/model.py
stream_translator_gpt/simul_streaming/simul_whisper/whisper/timing.py
stream_translator_gpt/simul_streaming/simul_whisper/whisper/tokenizer.py
stream_translator_gpt/simul_streaming/simul_whisper/whisper/triton_ops.py
stream_translator_gpt/simul_streaming/simul_whisper/whisper/utils.py
stream_translator_gpt/simul_streaming/simul_whisper/whisper/version.py
stream_translator_gpt/simul_streaming/simul_whisper/whisper/assets/gpt2.tiktoken
stream_translator_gpt/simul_streaming/simul_whisper/whisper/assets/mel_filters.npz
stream_translator_gpt/simul_streaming/simul_whisper/whisper/assets/multilingual.tiktoken
stream_translator_gpt/simul_streaming/simul_whisper/whisper/normalizers/__init__.py
stream_translator_gpt/simul_streaming/simul_whisper/whisper/normalizers/basic.py
stream_translator_gpt-2026.1.31.dist-info/licenses/LICENSE
stream_translator_gpt-2026.1.31.dist-info/METADATA
stream_translator_gpt-2026.1.31.dist-info/WHEEL
stream_translator_gpt-2026.1.31.dist-info/entry_points.txt
stream_translator_gpt-2026.1.31.dist-info/top_level.txt
stream_translator_gpt-2026.1.31.dist-info/RECORD
