Metadata-Version: 2.4
Name: stream-translator-gpt
Version: 2026.1.31
Summary: Command line tool to transcribe & translate audio from livestreams in real time
Author-email: ion <ionicbond3@gmail.com>
Project-URL: Homepage, https://github.com/ionic-bond/stream-translator-gpt
Project-URL: Issues, https://github.com/ionic-bond/stream-translator-gpt/issues
Keywords: translator,translation,translate,transcribe,yt-dlp,vad,whisper,faster-whisper,whisper-api,gpt,gemini
Classifier: Topic :: Multimedia :: Sound/Audio :: Analysis
Classifier: Development Status :: 5 - Production/Stable
Classifier: Environment :: Console
Classifier: Programming Language :: Python :: 3
Classifier: Programming Language :: Python :: 3 :: Only
Classifier: Programming Language :: Python :: 3.8
Classifier: Programming Language :: Python :: 3.9
Classifier: Programming Language :: Python :: 3.10
Classifier: Programming Language :: Python :: 3.11
Classifier: Programming Language :: Python :: 3.12
Classifier: License :: OSI Approved :: MIT License
Classifier: Operating System :: OS Independent
Requires-Python: >=3.8
License-File: LICENSE
Requires-Dist: numpy
Requires-Dist: scipy
Requires-Dist: yt-dlp>=2025.11.12
Requires-Dist: ffmpeg-python<0.3,>=0.2.0
Requires-Dist: pyaudiowpatch<0.3,>=0.2.12; sys_platform == "win32"
Requires-Dist: openai-whisper==20250625
Requires-Dist: faster-whisper<2.0.0,>=1.1.1
Requires-Dist: openai<3.0,>=2.0
Requires-Dist: google-genai<2.0,>=1.0
Requires-Dist: httpx<1.0,>=0.26.0
Provides-Extra: webui
Requires-Dist: gradio<6.0,>=5.0; extra == "webui"
Requires-Dist: platformdirs>=4.0; extra == "webui"
Dynamic: license-file
